information_flow_analysis/__init__.py
information_flow_analysis/analysis.py
information_flow_analysis/explicit.py
information_flow_analysis/implicit.py
information_flow_analysis/information.py
information_flow_analysis/out.py
information_flow_analysis/progress.py
information_flow_analysis/rda.py
information_flow_analysis/termination.py
information_flow_analysis/timing.py
information_flow_analysis-0.1.5.dist-info/METADATA
information_flow_analysis-0.1.5.dist-info/WHEEL
information_flow_analysis-0.1.5.dist-info/top_level.txt
information_flow_analysis-0.1.5.dist-info/RECORD
