Metadata-Version: 2.1
Name: information-flow-analysis
Version: 0.1.5
Summary: Information Flow Control library for binaries using angr
Home-page: UNKNOWN
Author: Kristoffer Astrup and Sebastian Olsen
License: MIT
Platform: UNKNOWN
Requires-Dist: angr
Requires-Dist: angr-utils
Requires-Dist: pydot
Requires-Dist: bingraphvis
Requires-Dist: networkx
Requires-Dist: matplotlib
